tilemapgen/__init__.py
tilemapgen/commands.py
tilemapgen/configuration.py
tilemapgen/logging.py
tilemapgen/stable_diffusion.py
tilemapgen/utils.py
tilemapgen-0.0.1.data/scripts/tilemapgen
tilemapgen-0.0.1.dist-info/LICENSE
tilemapgen-0.0.1.dist-info/METADATA
tilemapgen-0.0.1.dist-info/WHEEL
tilemapgen-0.0.1.dist-info/top_level.txt
tilemapgen-0.0.1.dist-info/RECORD
